comics_down/__init__.py
comics_down/console.py
comics_down/conf/__init__.py
comics_down/conf/common_website_driver.json
comics_down/conf/config.xml
comics_down/conf/common_website_dirver/77mh.xml
comics_down/conf/common_website_dirver/__init__.py
comics_down/conf/common_website_dirver/edddh.xml
comics_down/conf/common_website_dirver/mangabz.xml
comics_down/down_driver/__init__.py
comics_down/down_driver/aria2_down_driver.py
comics_down/down_driver/ftp_down_driver.py
comics_down/down_driver/http_down_driver.py
comics_down/down_driver/m3u8_down_driver.py
comics_down/down_driver/youget_down_driver.py
comics_down/i18n/__init__.py
comics_down/i18n/message_zh_cn.json
comics_down/lib/__init__.py
comics_down/lib/auto_analyse.py
comics_down/lib/comics_down_cmd.py
comics_down/lib/core.py
comics_down/lib/m3u8_downloader.py
comics_down/lib/webdriver_tool.py
comics_down/lib/proxy/__init__.py
comics_down/lib/proxy/selenium_feign_proxy.py
comics_down/website_driver/__init__.py
comics_down/website_driver/common_website_driver.py
comics_down/website_driver/youku_website_driver.py
comics_down-0.2.0.dist-info/LICENSE
comics_down-0.2.0.dist-info/METADATA
comics_down-0.2.0.dist-info/WHEEL
comics_down-0.2.0.dist-info/entry_points.txt
comics_down-0.2.0.dist-info/top_level.txt
comics_down-0.2.0.dist-info/RECORD
